Metadata-Version: 1.0
Name: alanmorrisudacity-distributions
Version: 0.1
Summary: Gaussian and Binomial distributions
Home-page: UNKNOWN
Author: Alan Morris
Author-email: morrisalan@gmail.com
License: UNKNOWN
Platform: UNKNOWN
